{"Pnw7eSsapWuPzLRbGoZl0w==":"mbr-192x179.jpg","cJqLwy9Nff2u0fG3701jrA==":"haalogo-122x46.png","MhZBOVqa2Avcgsqvn33BsQ==":"haalogo-v2yellow-254x95.png","2dsWNmdPJh9V3Dw3frHK5Q==":"mbr-1920x960.jpg","YG9Vr8NkZ+SmvxQVhY64jA==":"mbr-1920x1276.jpg","JQ/z+d2mA6bCvOB0AbfRdA==":"haa%20convention%202019v5-924x693.png","Ap7sAb31ky7gqNud1DA3bw==":"haalogo2019logoofficialtransparentw-478x215.png","UGXPVopGiaOu8HB7hARwDA==":"mbr-1920x1281.jpg","m8qM3lNStm2bONw1Ryck3g==":"rani%20shashiprabha-haa-yakshamitra-924x520.png","nlmjzZ9qbcnj0mniI8CVcg==":"mbr-688x683.jpg","XKn7i5hXSFuc8wAgC5nnXA==":"mbr-924x674.jpg","MUlvUMRk/c3A7LtW65fWPw==":"mbr-478x287.jpg","u6vaaISZNk8tX6MK6ObZPA==":"mbr-436x373.jpg","vBiU5QH36fvepyQUGsaq7w==":"mbr-1072x716.jpg","ezF0k6PSi4eAJlgB5G1MXQ==":"mbr-436x245.jpg","Z2sP4hVRRuULnj5i0U4tRA==":"0001-2000x2588.jpg","WdpTC4821nBjXZPmPWwLYg==":"haa%20convention%202019v5-1024x768.png","aa0KQAaF3VIhtfHvi1QVRA==":"haa2019canadaeasttour-1350x650.png","ZoEw7j/eozVJaVeZbSsf7Q==":"haa2019youthfocus-1350x650.png","tGgVNTG5asucsKSRBYftJA==":"haabanner2019-1-2000x703.png","WfotZ+0SG2J6WhRiF2i/iQ==":"haa2019-layagayanalaasya-1350x650.png"}